odoo8_addon_web_clean_navbar-8.0.1.0.0.99.dev2-py2.7-nspkg.pth
odoo8_addon_web_clean_navbar-8.0.1.0.0.99.dev2.dist-info/DESCRIPTION.rst
odoo8_addon_web_clean_navbar-8.0.1.0.0.99.dev2.dist-info/METADATA
odoo8_addon_web_clean_navbar-8.0.1.0.0.99.dev2.dist-info/RECORD
odoo8_addon_web_clean_navbar-8.0.1.0.0.99.dev2.dist-info/WHEEL
odoo8_addon_web_clean_navbar-8.0.1.0.0.99.dev2.dist-info/metadata.json
odoo8_addon_web_clean_navbar-8.0.1.0.0.99.dev2.dist-info/namespace_packages.txt
odoo8_addon_web_clean_navbar-8.0.1.0.0.99.dev2.dist-info/top_level.txt
odoo_addons/web_clean_navbar/README.rst
odoo_addons/web_clean_navbar/__init__.py
odoo_addons/web_clean_navbar/__openerp__.py
odoo_addons/web_clean_navbar/i18n/web_clean_navbar.pot
odoo_addons/web_clean_navbar/static/description/icon.png
odoo_addons/web_clean_navbar/static/description/index.html
odoo_addons/web_clean_navbar/static/description/navbar1.png
odoo_addons/web_clean_navbar/static/src/css/clean_navbar.css
odoo_addons/web_clean_navbar/views/clean_navbar.xml
