Metadata-Version: 2.0
Name: odoo8-addon-web-clean-navbar
Version: 8.0.1.0.0.99.dev2
Summary: Better visibility for the backend's main menu
Home-page: https://github.com/OCA/web
Author: Equitania Software GmbH,Odoo Community Association (OCA)
Author-email: support@odoo-community.org
License: AGPL-3
Platform: UNKNOWN
Classifier: Programming Language :: Python
Classifier: Framework :: Odoo
Classifier: License :: OSI Approved :: GNU Affero General Public License v3
Requires-Python: ~=2.7
Requires-Dist: odoo (<9.0a,>=8.0a)
